Workbook

Sheet README
A1: Project finance model (formula version)
A2: Hypothetical inputs. Not a real project, not market terms, not advice, and not any rating agency's model or criteria.
A4: What it does
A5: Sizes senior debt on the sponsor case as min(PV of CFADS over the tenor / target DSCR, gearing cap x total uses),
A6: sculpts repayments to the resulting DSCR, then runs the active stress on Inputs against that frozen schedule:
A7: DSCR, LLCR, PLCR, lock-up and default-level tests, payment shortfalls, distributions and equity IRR.
A8: It reproduces src/projectfinancelab/model.py; Checks compares the two.
A10: How to use
A11: Edit only blue cells on Inputs. Stress cells (rows 26-29) change Analysis only; sizing never sees the stress.
A12: Debt and total uses (rows 32-33) are pasted values: IDC and the fee depend on the debt, so the model is circular.
A13: After changing any sponsor input, paste Checks!C5 into Inputs!C32 and Checks!C6 into Inputs!C33 and repeat
A14: until both 'converged' checks are TRUE (a few rounds), or run project-finance-lab and paste its values.
... A20: Method and every formula: docs/model_spec.md. Limitations: docs/limitations.md.

Sheet Inputs
A1: Inputs (edit blue cells only; all hypothetical)
B3: Sponsor case and financing terms
F4: Legend
B5: Construction years (1-3) | C5: 2 | F5: Blue text = input
B6: Capex, before IDC and fees (m) | C6: 400 | F6: Yellow fill = key assumption or pasted value
B7: Capex share, construction year 1 | C7: 0.45 | F7: Source: examples/project_hypothetical.json (hypothetical)
B8: Capex share, construction year 2 | C8: 0.55
B9: Capex share, construction year 3 | C9: 0 | F9: Shipped cases (illustrative layering, not any agency's rating case)
B10: Operating years (max 30) | C10: 25 | F10: sponsor: no stress
B11: Revenue, operating year 1 (m) | C11: 62 | F11: base: revenue_haircut 0.05, opex_increase 0.05
B12: Revenue growth a year | C12: 0.02 | F12: downside: revenue_haircut 0.12, opex_increase 0.15, capex_overrun 0.05
B13: Opex, operating year 1 (m) | C13: 14 | F13: delay_6m: delay_months 6
B14: Opex growth a year | C14: 0.025
B15: Tax rate (on EBITDA - depreciation, floor 0) | C15: 0.25
B16: Depreciation years (straight line on capex) | C16: 20
B17: Debt all-in fixed rate | C17: 0.06
B18: Debt tenor, operating years (< operating years) | C18: 18
B19: Target DSCR for sizing | C19: 1.35
B20: Maximum gearing (debt / total uses) | C20: 0.9
B21: Upfront fee (share of debt) | C21: 0.015
B22: Lock-up DSCR | C22: 1.15
B23: Default-level DSCR | C23: 1.05
B25: Active stress (shipped: 'downside' case; stress never changes the debt)
B26: Stress: revenue haircut | C26: 0.12
B27: Stress: opex increase | C27: 0.15
B28: Stress: COD delay, months (revenue lost in year 1) | C28: 0
B29: Stress: capex overrun, equity-funded (share of capex) | C29: 0.05
B31: Circular values, pasted
B32: Debt (pasted; see README) | C32: 369.5367 | D32: Paste from Checks!C5 once converged
B33: Total uses (pasted; see README) | C33: 415.44543 | D33: Paste from Checks!C6 once converged

Sheet Construction
A1: Construction: capex, fee, IDC and pro-rata funding
B4: Construction year | C4: 1 | D4: 2 | E4: 3
B5: Active | C5: =IF(C$4<=Inputs!$C$5,1,0) -> 1 | D5: =IF(D$4<=Inputs!$C$5,1,0) -> 1 | E5: =IF(E$4<=Inputs!$C$5,1,0) -> 0
B6: Capex | C6: =Inputs!$C$6*INDEX(Inputs!$C$7:$C$9,C$4)*C5 -> 180 | D6: =Inputs!$C$6*INDEX(Inputs!$C$7:$C$9,D$4)*D5 -> 220 | E6: =Inputs!$C$6*INDEX(Inputs!$C$7:$C$9,E$4)*E5 -> 0
B7: Upfront fee | C7: =IF(C$4=1,Inputs!$C$21*Inputs!$C$32,0) -> 5.5430505 | D7: =IF(D$4=1,Inputs!$C$21*Inputs!$C$32,0) -> 0 | E7: =IF(E$4=1,Inputs!$C$21*Inputs!$C$32,0) -> 0
B8: Opening debt balance | C8: 0 | D8: =C12 -> 165.03964 | E8: =D12 -> 369.5367
B9: IDC (rate x opening balance, capitalised) | C9: =Inputs!$C$17*C8*C5 -> 0 | D9: =Inputs!$C$17*D8*D5 -> 9.9023787 | E9: =Inputs!$C$17*E8*E5 -> 0
B10: Uses | C10: =C6+C7+C9 -> 185.54305 | D10: =D6+D7+D9 -> 229.90238 | E10: =E6+E7+E9 -> 0
B11: Debt draw (debt share x uses) | C11: =$C$16*C10 -> 165.03964 | D11: =$C$16*D10 -> 204.49705 | E11: =$C$16*E10 -> 0
B12: Closing debt balance | C12: =C8+C11 -> 165.03964 | D12: =D8+D11 -> 369.5367 | E12: =E8+E11 -> 369.5367
B13: Equity | C13: =C10-C11 -> 20.503406 | D13: =D10-D11 -> 25.405326 | E13: =E10-E11 -> 0
B15: Total uses (calculated) | C15: =SUM(C10:E10) -> 415.44543
B16: Debt share (pasted debt / pasted uses) | C16: =Inputs!C32/Inputs!C33 -> 0.88949516
B17: Debt balance at COD | C17: =E12 -> 369.5367
B18: Total equity | C18: =SUM(C13:E13) -> 45.908732

Sheet Operations
A1: Operations: sponsor case, debt sizing and the frozen repayment schedule
B4: Operating year | D4: 1 | E4: 2 | F4: 3 | G4: 4 | H4: 5 | I4: 6 | J4: 7 | K4: 8 | L4: 9 | M4: 10 | N4: 11 | O4: 12 | P4: 13 | Q4: 14 | R4: 15 | S4: 16 | T4: 17 | U4: 18 | V4: 19 | W4: 20 | X4: 21 | Y4: 22 | Z4: 23 | AA4: 24 | AB4: 25 | AC4: 26 | AD4: 27 | AE4: 28 | AF4: 29 | AG4: 30
B5: Operating | D5: =IF(D$4<=Inputs!$C$10,1,0) -> 1 | E5: =IF(E$4<=Inputs!$C$10,1,0) -> 1 | F5: =IF(F$4<=Inputs!$C$10,1,0) -> 1 | G5: =IF(G$4<=Inputs!$C$10,1,0) -> 1 | H5: =IF(H$4<=Inputs!$C$10,1,0) -> 1 | I5: =IF(I$4<=Inputs!$C$10,1,0) -> 1 | J5: =IF(J$4<=Inputs!$C$10,1,0) -> 1 | K5: =IF(K$4<=Inputs!$C$10,1,0) -> 1 | ... AG5: =IF(AG$4<=Inputs!$C$10,1,0) -> 0
B6: In debt tenor | D6: =IF(D$4<=Inputs!$C$18,1,0)*D5 -> 1 | E6: =IF(E$4<=Inputs!$C$18,1,0)*E5 -> 1 | F6: =IF(F$4<=Inputs!$C$18,1,0)*F5 -> 1 | G6: =IF(G$4<=Inputs!$C$18,1,0)*G5 -> 1 | H6: =IF(H$4<=Inputs!$C$18,1,0)*H5 -> 1 | I6: =IF(I$4<=Inputs!$C$18,1,0)*I5 -> 1 | J6: =IF(J$4<=Inputs!$C$18,1,0)*J5 -> 1 | K6: =IF(K$4<=Inputs!$C$18,1,0)*K5 -> 1 | ... AG6: =IF(AG$4<=Inputs!$C$18,1,0)*AG5 -> 0
B7: Revenue | D7: =Inputs!$C$11*(1+Inputs!$C$12)^(D$4-1)*D5 -> 62 | E7: =Inputs!$C$11*(1+Inputs!$C$12)^(E$4-1)*E5 -> 63.24 | F7: =Inputs!$C$11*(1+Inputs!$C$12)^(F$4-1)*F5 -> 64.5048 | G7: =Inputs!$C$11*(1+Inputs!$C$12)^(G$4-1)*G5 -> 65.794896 | H7: =Inputs!$C$11*(1+Inputs!$C$12)^(H$4-1)*H5 -> 67.110794 | I7: =Inputs!$C$11*(1+Inputs!$C$12)^(I$4-1)*I5 -> 68.45301 | J7: =Inputs!$C$11*(1+Inputs!$C$12)^(J$4-1)*J5 -> 69.82207 | K7: =Inputs!$C$11*(1+Inputs!$C$12)^(K$4-1)*K5 -> 71.218511 | ... AG7: =Inputs!$C$11*(1+Inputs!$C$12)^(AG$4-1)*AG5 -> 0
B8: Opex | D8: =Inputs!$C$13*(1+Inputs!$C$14)^(D$4-1)*D5 -> 14 | E8: =Inputs!$C$13*(1+Inputs!$C$14)^(E$4-1)*E5 -> 14.35 | F8: =Inputs!$C$13*(1+Inputs!$C$14)^(F$4-1)*F5 -> 14.70875 | G8: =Inputs!$C$13*(1+Inputs!$C$14)^(G$4-1)*G5 -> 15.076469 | H8: =Inputs!$C$13*(1+Inputs!$C$14)^(H$4-1)*H5 -> 15.45338 | I8: =Inputs!$C$13*(1+Inputs!$C$14)^(I$4-1)*I5 -> 15.839715 | J8: =Inputs!$C$13*(1+Inputs!$C$14)^(J$4-1)*J5 -> 16.235708 | K8: =Inputs!$C$13*(1+Inputs!$C$14)^(K$4-1)*K5 -> 16.641601 | ... AG8: =Inputs!$C$13*(1+Inputs!$C$14)^(AG$4-1)*AG5 -> 0
B9: EBITDA | D9: =D7-D8 -> 48 | E9: =E7-E8 -> 48.89 | F9: =F7-F8 -> 49.79605 | G9: =G7-G8 -> 50.718427 | H9: =H7-H8 -> 51.657413 | I9: =I7-I8 -> 52.613295 | J9: =J7-J8 -> 53.586362 | K9: =K7-K8 -> 54.576911 | ... AG9: =AG7-AG8 -> 0
B10: Depreciation | D10: =IF(D$4<=Inputs!$C$16,Inputs!$C$6/Inputs!$C$16,0)*D5 -> 20 | E10: =IF(E$4<=Inputs!$C$16,Inputs!$C$6/Inputs!$C$16,0)*E5 -> 20 | F10: =IF(F$4<=Inputs!$C$16,Inputs!$C$6/Inputs!$C$16,0)*F5 -> 20 | G10: =IF(G$4<=Inputs!$C$16,Inputs!$C$6/Inputs!$C$16,0)*G5 -> 20 | H10: =IF(H$4<=Inputs!$C$16,Inputs!$C$6/Inputs!$C$16,0)*H5 -> 20 | I10: =IF(I$4<=Inputs!$C$16,Inputs!$C$6/Inputs!$C$16,0)*I5 -> 20 | J10: =IF(J$4<=Inputs!$C$16,Inputs!$C$6/Inputs!$C$16,0)*J5 -> 20 | K10: =IF(K$4<=Inputs!$C$16,Inputs!$C$6/Inputs!$C$16,0)*K5 -> 20 | ... AG10: =IF(AG$4<=Inputs!$C$16,Inputs!$C$6/Inputs!$C$16,0)*AG5 -> 0
B11: Tax | D11: =Inputs!$C$15*MAX(0,D9-D10) -> 7 | E11: =Inputs!$C$15*MAX(0,E9-E10) -> 7.2225 | F11: =Inputs!$C$15*MAX(0,F9-F10) -> 7.4490125 | G11: =Inputs!$C$15*MAX(0,G9-G10) -> 7.6796068 | H11: =Inputs!$C$15*MAX(0,H9-H10) -> 7.9143534 | I11: =Inputs!$C$15*MAX(0,I9-I10) -> 8.1533237 | J11: =Inputs!$C$15*MAX(0,J9-J10) -> 8.3965905 | K11: =Inputs!$C$15*MAX(0,K9-K10) -> 8.6442277 | ... AG11: =Inputs!$C$15*MAX(0,AG9-AG10) -> 0
B12: CFADS (sponsor case) | D12: =D9-D11 -> 41 | E12: =E9-E11 -> 41.6675 | F12: =F9-F11 -> 42.347037 | G12: =G9-G11 -> 43.03882 | H12: =H9-H11 -> 43.74306 | I12: =I9-I11 -> 44.459971 | J12: =J9-J11 -> 45.189772 | K12: =K9-K11 -> 45.932683 | ... AG12: =AG9-AG11 -> 0
B13: Discount factor, end of year | D13: =1/(1+Inputs!$C$17)^D$4 -> 0.94339623 | E13: =1/(1+Inputs!$C$17)^E$4 -> 0.88999644 | F13: =1/(1+Inputs!$C$17)^F$4 -> 0.83961928 | G13: =1/(1+Inputs!$C$17)^G$4 -> 0.79209366 | H13: =1/(1+Inputs!$C$17)^H$4 -> 0.74725817 | I13: =1/(1+Inputs!$C$17)^I$4 -> 0.70496054 | J13: =1/(1+Inputs!$C$17)^J$4 -> 0.66505711 | K13: =1/(1+Inputs!$C$17)^K$4 -> 0.62741237 | ... AG13: =1/(1+Inputs!$C$17)^AG$4 -> 0.17411013
B14: Discount factor, start of year | D14: =1/(1+Inputs!$C$17)^(D$4-1) -> 1 | E14: =1/(1+Inputs!$C$17)^(E$4-1) -> 0.94339623 | F14: =1/(1+Inputs!$C$17)^(F$4-1) -> 0.88999644 | G14: =1/(1+Inputs!$C$17)^(G$4-1) -> 0.83961928 | H14: =1/(1+Inputs!$C$17)^(H$4-1) -> 0.79209366 | I14: =1/(1+Inputs!$C$17)^(I$4-1) -> 0.74725817 | J14: =1/(1+Inputs!$C$17)^(J$4-1) -> 0.70496054 | K14: =1/(1+Inputs!$C$17)^(K$4-1) -> 0.66505711 | ... AG14: =1/(1+Inputs!$C$17)^(AG$4-1) -> 0.18455674
B16: Debt service (sculpted; frozen) | D16: =D6*D12/$C$34 -> 30.37037 | E16: =E6*E12/$C$34 -> 30.864815 | F16: =F6*F12/$C$34 -> 31.368176 | G16: =G6*G12/$C$34 -> 31.880608 | H16: =H6*H12/$C$34 -> 32.402267 | I16: =I6*I12/$C$34 -> 32.933312 | J16: =J6*J12/$C$34 -> 33.473905 | K16: =K6*K12/$C$34 -> 34.02421 | ... AG16: =AG6*AG12/$C$34 -> 0
B17: Opening balance | D17: =Construction!$C$17 -> 369.5367 | E17: =D20 -> 361.33853 | F17: =E20 -> 352.15403 | G17: =F20 -> 341.91509 | H17: =G20 -> 330.54939 | I17: =H20 -> 317.98009 | J17: =I20 -> 304.12558 | K17: =J20 -> 288.89921 | L17: =K20 -> 272.20895 | ... AG17: =AF20 -> -6.1106675e-13
B18: Interest | D18: =Inputs!$C$17*D17*D6 -> 22.172202 | E18: =Inputs!$C$17*E17*E6 -> 21.680312 | F18: =Inputs!$C$17*F17*F6 -> 21.129242 | G18: =Inputs!$C$17*G17*G6 -> 20.514905 | H18: =Inputs!$C$17*H17*H6 -> 19.832963 | I18: =Inputs!$C$17*I17*I6 -> 19.078805 | J18: =Inputs!$C$17*J17*J6 -> 18.247535 | K18: =Inputs!$C$17*K17*K6 -> 17.333952 | ... AG18: =Inputs!$C$17*AG17*AG6 -> 0
B19: Principal | D19: =D16-D18 -> 8.1981686 | E19: =E16-E18 -> 9.1845031 | F19: =F16-F18 -> 10.238934 | G19: =G16-G18 -> 11.365702 | H19: =H16-H18 -> 12.569303 | I19: =I16-I18 -> 13.854507 | J19: =J16-J18 -> 15.22637 | K19: =K16-K18 -> 16.690257 | ... AG19: =AG16-AG18 -> 0
B20: Closing balance | D20: =D17-D19 -> 361.33853 | E20: =E17-E19 -> 352.15403 | F20: =F17-F19 -> 341.91509 | G20: =G17-G19 -> 330.54939 | H20: =H17-H19 -> 317.98009 | I20: =I17-I19 -> 304.12558 | J20: =J17-J19 -> 288.89921 | K20: =K17-K19 -> 272.20895 | ... AG20: =AG17-AG19 -> -6.1106675e-13
B22: LLCR, sponsor case (must equal sculpting DSCR) | D22: =IF(D6=1,SUMPRODUCT(D12:$AG$12,D13:$AG$13,D6:$AG$6)/D14/D17,0) -> 1.35 | E22: =IF(E6=1,SUMPRODUCT(E12:$AG$12,E13:$AG$13,E6:$AG$6)/E14/E17,0) -> 1.35 | F22: =IF(F6=1,SUMPRODUCT(F12:$AG$12,F13:$AG$13,F6:$AG$6)/F14/F17,0) -> 1.35 | G22: =IF(G6=1,SUMPRODUCT(G12:$AG$12,G13:$AG$13,G6:$AG$6)/G14/G17,0) -> 1.35 | H22: =IF(H6=1,SUMPRODUCT(H12:$AG$12,H13:$AG$13,H6:$AG$6)/H14/H17,0) -> 1.35 | I22: =IF(I6=1,SUMPRODUCT(I12:$AG$12,I13:$AG$13,I6:$AG$6)/I14/I17,0) -> 1.35 | J22: =IF(J6=1,SUMPRODUCT(J12:$AG$12,J13:$AG$13,J6:$AG$6)/J14/J17,0) -> 1.35 | K22: =IF(K6=1,SUMPRODUCT(K12:$AG$12,K13:$AG$13,K6:$AG$6)/K14/K17,0) -> 1.35 | ... AG22: =IF(AG6=1,SUMPRODUCT(AG12:$AG$12,AG13:$AG$13,AG6:$AG$6)/AG14/AG17,0) -> 0
B29: Sizing
B30: PV at COD of sponsor CFADS over the tenor | C30: =SUMPRODUCT(D12:AG12,D13:AG13,D6:AG6) -> 498.87454
B31: Debt capacity at target DSCR | C31: =C30/Inputs!C19 -> 369.5367
B32: Gearing cap x total uses | C32: =Inputs!C20*Construction!C15 -> 373.90089
B33: Debt (calculated) = min of the two | C33: =MIN(C31,C32) -> 369.5367
B34: Sculpting DSCR = PV / pasted debt | C34: =C30/Inputs!C32 -> 1.35
B35: Binding constraint | C35: =IF(C31<=C32,"DSCR","gearing") -> DSCR
B36: Balance at maturity | C36: =INDEX(D20:AG20,1,Inputs!C18) -> -6.1106675e-13
B37: Sum of principal over the tenor | C37: =SUMPRODUCT(D19:AG19,D6:AG6) -> 369.5367
B38: Smallest principal payment in the tenor | C38: =_xlfn.MINIFS(D19:AG19,D6:AG6,1) -> 8.1981686

Sheet Analysis
A1: Analysis: active stress against the frozen debt schedule
B4: Operating year | D4: 1 | E4: 2 | F4: 3 | G4: 4 | H4: 5 | I4: 6 | J4: 7 | K4: 8 | L4: 9 | M4: 10 | N4: 11 | O4: 12 | P4: 13 | Q4: 14 | R4: 15 | S4: 16 | T4: 17 | U4: 18 | V4: 19 | W4: 20 | X4: 21 | Y4: 22 | Z4: 23 | AA4: 24 | AB4: 25 | AC4: 26 | AD4: 27 | AE4: 28 | AF4: 29 | AG4: 30
B5: Operating | D5: =Operations!D5 -> 1 | E5: =Operations!E5 -> 1 | F5: =Operations!F5 -> 1 | G5: =Operations!G5 -> 1 | H5: =Operations!H5 -> 1 | I5: =Operations!I5 -> 1 | J5: =Operations!J5 -> 1 | K5: =Operations!K5 -> 1 | ... AG5: =Operations!AG5 -> 0
B6: In debt tenor | D6: =Operations!D6 -> 1 | E6: =Operations!E6 -> 1 | F6: =Operations!F6 -> 1 | G6: =Operations!G6 -> 1 | H6: =Operations!H6 -> 1 | I6: =Operations!I6 -> 1 | J6: =Operations!J6 -> 1 | K6: =Operations!K6 -> 1 | ... AG6: =Operations!AG6 -> 0
B7: Revenue (stressed) | D7: =Operations!D7*(1-Inputs!$C$26)*IF(D$4=1,1-Inputs!$C$28/12,1) -> 54.56 | E7: =Operations!E7*(1-Inputs!$C$26)*IF(E$4=1,1-Inputs!$C$28/12,1) -> 55.6512 | F7: =Operations!F7*(1-Inputs!$C$26)*IF(F$4=1,1-Inputs!$C$28/12,1) -> 56.764224 | G7: =Operations!G7*(1-Inputs!$C$26)*IF(G$4=1,1-Inputs!$C$28/12,1) -> 57.899508 | H7: =Operations!H7*(1-Inputs!$C$26)*IF(H$4=1,1-Inputs!$C$28/12,1) -> 59.057499 | I7: =Operations!I7*(1-Inputs!$C$26)*IF(I$4=1,1-Inputs!$C$28/12,1) -> 60.238649 | J7: =Operations!J7*(1-Inputs!$C$26)*IF(J$4=1,1-Inputs!$C$28/12,1) -> 61.443422 | K7: =Operations!K7*(1-Inputs!$C$26)*IF(K$4=1,1-Inputs!$C$28/12,1) -> 62.67229 | ... AG7: =Operations!AG7*(1-Inputs!$C$26)*IF(AG$4=1,1-Inputs!$C$28/12,1) -> 0
B8: Opex (stressed) | D8: =Operations!D8*(1+Inputs!$C$27) -> 16.1 | E8: =Operations!E8*(1+Inputs!$C$27) -> 16.5025 | F8: =Operations!F8*(1+Inputs!$C$27) -> 16.915063 | G8: =Operations!G8*(1+Inputs!$C$27) -> 17.337939 | H8: =Operations!H8*(1+Inputs!$C$27) -> 17.771388 | I8: =Operations!I8*(1+Inputs!$C$27) -> 18.215672 | J8: =Operations!J8*(1+Inputs!$C$27) -> 18.671064 | K8: =Operations!K8*(1+Inputs!$C$27) -> 19.137841 | ... AG8: =Operations!AG8*(1+Inputs!$C$27) -> 0
B9: EBITDA | D9: =D7-D8 -> 38.46 | E9: =E7-E8 -> 39.1487 | F9: =F7-F8 -> 39.849162 | G9: =G7-G8 -> 40.561569 | H9: =H7-H8 -> 41.286111 | I9: =I7-I8 -> 42.022976 | J9: =J7-J8 -> 42.772358 | K9: =K7-K8 -> 43.534449 | ... AG9: =AG7-AG8 -> 0
B10: Tax | D10: =Inputs!$C$15*MAX(0,D9-Operations!D10) -> 4.615 | E10: =Inputs!$C$15*MAX(0,E9-Operations!E10) -> 4.787175 | F10: =Inputs!$C$15*MAX(0,F9-Operations!F10) -> 4.9622904 | G10: =Inputs!$C$15*MAX(0,G9-Operations!G10) -> 5.1403924 | H10: =Inputs!$C$15*MAX(0,H9-Operations!H10) -> 5.3215278 | I10: =Inputs!$C$15*MAX(0,I9-Operations!I10) -> 5.5057441 | J10: =Inputs!$C$15*MAX(0,J9-Operations!J10) -> 5.6930894 | K10: =Inputs!$C$15*MAX(0,K9-Operations!K10) -> 5.8836123 | ... AG10: =Inputs!$C$15*MAX(0,AG9-Operations!AG10) -> 0
B11: CFADS (stressed) | D11: =D9-D10 -> 33.845 | E11: =E9-E10 -> 34.361525 | F11: =F9-F10 -> 34.886871 | G11: =G9-G10 -> 35.421177 | H11: =H9-H10 -> 35.964583 | I11: =I9-I10 -> 36.517232 | J11: =J9-J10 -> 37.079268 | K11: =K9-K10 -> 37.650837 | ... AG11: =AG9-AG10 -> 0
B12: Debt service (frozen, from Operations) | D12: =Operations!D16 -> 30.37037 | E12: =Operations!E16 -> 30.864815 | F12: =Operations!F16 -> 31.368176 | G12: =Operations!G16 -> 31.880608 | H12: =Operations!H16 -> 32.402267 | I12: =Operations!I16 -> 32.933312 | J12: =Operations!J16 -> 33.473905 | K12: =Operations!K16 -> 34.02421 | ... AG12: =Operations!AG16 -> 0
B13: DSCR | D13: =IF(D6=1,D11/D12,"") -> 1.1144085 | E13: =IF(E6=1,E11/E12,"") -> 1.1132911 | F13: =IF(F6=1,F11/F12,"") -> 1.112174 | G13: =IF(G6=1,G11/G12,"") -> 1.1110571 | H13: =IF(H6=1,H11/H12,"") -> 1.1099404 | I13: =IF(I6=1,I11/I12,"") -> 1.1088236 | J13: =IF(J6=1,J11/J12,"") -> 1.1077067 | K13: =IF(K6=1,K11/K12,"") -> 1.1065896 | ... AG13: =IF(AG6=1,AG11/AG12,"")
B14: Opening balance | D14: =Operations!D17 -> 369.5367 | E14: =Operations!E17 -> 361.33853 | F14: =Operations!F17 -> 352.15403 | G14: =Operations!G17 -> 341.91509 | H14: =Operations!H17 -> 330.54939 | I14: =Operations!I17 -> 317.98009 | J14: =Operations!J17 -> 304.12558 | K14: =Operations!K17 -> 288.89921 | ... AG14: =Operations!AG17 -> -6.1106675e-13
B15: LLCR | D15: =IF(D6=1,SUMPRODUCT(D11:$AG$11,Operations!D13:$AG$13,D6:$AG$6)/Operations!D14/D14,"") -> 1.1061578 | E15: =IF(E6=1,SUMPRODUCT(E11:$AG$11,Operations!E13:$AG$13,E6:$AG$6)/Operations!E14/E14,"") -> 1.1054644 | F15: =IF(F6=1,SUMPRODUCT(F11:$AG$11,Operations!F13:$AG$13,F6:$AG$6)/Operations!F14/F14,"") -> 1.1047784 | G15: =IF(G6=1,SUMPRODUCT(G11:$AG$11,Operations!G13:$AG$13,G6:$AG$6)/Operations!G14/G14,"") -> 1.1040999 | H15: =IF(H6=1,SUMPRODUCT(H11:$AG$11,Operations!H13:$AG$13,H6:$AG$6)/Operations!H14/H14,"") -> 1.1034289 | I15: =IF(I6=1,SUMPRODUCT(I11:$AG$11,Operations!I13:$AG$13,I6:$AG$6)/Operations!I14/I14,"") -> 1.1027654 | J15: =IF(J6=1,SUMPRODUCT(J11:$AG$11,Operations!J13:$AG$13,J6:$AG$6)/Operations!J14/J14,"") -> 1.1021093 | K15: =IF(K6=1,SUMPRODUCT(K11:$AG$11,Operations!K13:$AG$13,K6:$AG$6)/Operations!K14/K14,"") -> 1.1014608 | ... AG15: =IF(AG6=1,SUMPRODUCT(AG11:$AG$11,Operations!AG13:$AG$13,AG6:$AG$6)/Operations!AG14/AG14,"")
B16: Lock-up (DSCR < lock-up level) | D16: =IF(D6=1,IF(D13<Inputs!$C$22,1,0),0) -> 1 | E16: =IF(E6=1,IF(E13<Inputs!$C$22,1,0),0) -> 1 | F16: =IF(F6=1,IF(F13<Inputs!$C$22,1,0),0) -> 1 | G16: =IF(G6=1,IF(G13<Inputs!$C$22,1,0),0) -> 1 | H16: =IF(H6=1,IF(H13<Inputs!$C$22,1,0),0) -> 1 | I16: =IF(I6=1,IF(I13<Inputs!$C$22,1,0),0) -> 1 | J16: =IF(J6=1,IF(J13<Inputs!$C$22,1,0),0) -> 1 | K16: =IF(K6=1,IF(K13<Inputs!$C$22,1,0),0) -> 1 | ... AG16: =IF(AG6=1,IF(AG13<Inputs!$C$22,1,0),0) -> 0
B17: Default level (DSCR < default level) | D17: =IF(D6=1,IF(D13<Inputs!$C$23,1,0),0) -> 0 | E17: =IF(E6=1,IF(E13<Inputs!$C$23,1,0),0) -> 0 | F17: =IF(F6=1,IF(F13<Inputs!$C$23,1,0),0) -> 0 | G17: =IF(G6=1,IF(G13<Inputs!$C$23,1,0),0) -> 0 | H17: =IF(H6=1,IF(H13<Inputs!$C$23,1,0),0) -> 0 | I17: =IF(I6=1,IF(I13<Inputs!$C$23,1,0),0) -> 0 | J17: =IF(J6=1,IF(J13<Inputs!$C$23,1,0),0) -> 0 | K17: =IF(K6=1,IF(K13<Inputs!$C$23,1,0),0) -> 0 | ... AG17: =IF(AG6=1,IF(AG13<Inputs!$C$23,1,0),0) -> 0
B18: Cash available (b/f + CFADS - debt service) | D18: =C20+D11-D12 -> 3.4746296 | E18: =D20+E11-E12 -> 6.9713398 | F18: =E20+F11-F12 -> 10.490035 | G18: =F20+G11-G12 -> 14.030604 | H18: =G20+H11-H12 -> 17.592921 | I18: =H20+I11-I12 -> 21.176841 | J18: =I20+J11-J12 -> 24.782205 | K18: =J20+K11-K12 -> 28.408832 | ... AG18: =AF20+AG11-AG12 -> 0
B19: Payment shortfall | D19: =MAX(0,-D18) -> 0 | E19: =MAX(0,-E18) -> 0 | F19: =MAX(0,-F18) -> 0 | G19: =MAX(0,-G18) -> 0 | H19: =MAX(0,-H18) -> 0 | I19: =MAX(0,-I18) -> 0 | J19: =MAX(0,-J18) -> 0 | K19: =MAX(0,-K18) -> 0 | ... AG19: =MAX(0,-AG18) -> 0
B20: Cash carried forward | C20: 0 | D20: =MAX(0,D18)-D21 -> 3.4746296 | E20: =MAX(0,E18)-E21 -> 6.9713398 | F20: =MAX(0,F18)-F21 -> 10.490035 | G20: =MAX(0,G18)-G21 -> 14.030604 | H20: =MAX(0,H18)-H21 -> 17.592921 | I20: =MAX(0,I18)-I21 -> 21.176841 | J20: =MAX(0,J18)-J21 -> 24.782205 | K20: =MAX(0,K18)-K21 -> 28.408832 | ... AG20: =MAX(0,AG18)-AG21 -> 0
B21: Distributions | D21: =IF(D16=1,0,MAX(0,D18)) -> 0 | E21: =IF(E16=1,0,MAX(0,E18)) -> 0 | F21: =IF(F16=1,0,MAX(0,F18)) -> 0 | G21: =IF(G16=1,0,MAX(0,G18)) -> 0 | H21: =IF(H16=1,0,MAX(0,H18)) -> 0 | I21: =IF(I16=1,0,MAX(0,I18)) -> 0 | J21: =IF(J16=1,0,MAX(0,J18)) -> 0 | K21: =IF(K16=1,0,MAX(0,K18)) -> 0 | ... AG21: =IF(AG16=1,0,MAX(0,AG18)) -> 0
B24: Equity cash flows: last 3 construction slots, then operating years | D24: =IF((Inputs!$C$5-2+0)>=1,-INDEX(Construction!$C$13:$E$13,1,(Inputs!$C$5-2+0))-IF((Inputs!$C$5-2+0)=Inputs!$C$5,Inputs!$C$29*Inputs!$C$6,0),0) -> 0 | E24: =IF((Inputs!$C$5-2+1)>=1,-INDEX(Construction!$C$13:$E$13,1,(Inputs!$C$5-2+1))-IF((Inputs!$C$5-2+1)=Inputs!$C$5,Inputs!$C$29*Inputs!$C$6,0),0) -> -20.503406 | F24: =IF((Inputs!$C$5-2+2)>=1,-INDEX(Construction!$C$13:$E$13,1,(Inputs!$C$5-2+2))-IF((Inputs!$C$5-2+2)=Inputs!$C$5,Inputs!$C$29*Inputs!$C$6,0),0) -> -45.405326 | G24: =D21 -> 0 | H24: =E21 -> 0 | I24: =F21 -> 0 | J24: =G21 -> 0 | K24: =H21 -> 0 | L24: =I21 -> 0 | M24: =J21 -> 0 | N24: =K21 -> 0 | ... AJ24: =AG21 -> 0
B27: Results
B28: Minimum DSCR | C28: =MIN(D13:AG13) -> 1.0953855
B29: Average DSCR | C29: =AVERAGE(D13:AG13) -> 1.1049074
B30: LLCR at COD | C30: =D15 -> 1.1061578
B31: Minimum LLCR | C31: =MIN(D15:AG15) -> 1.0953855
B32: PLCR at COD | C32: =SUMPRODUCT(D11:AG11,Operations!D13:AG13,D5:AG5)/D14 -> 1.3349882
B33: Lock-up years | C33: =SUM(D16:AG16) -> 18
B34: Default-level years | C34: =SUM(D17:AG17) -> 0
B35: Total payment shortfall | C35: =SUM(D19:AG19) -> 0
B36: Total distributions | C36: =SUM(D21:AG21) -> 368.13904
B37: Equity IRR (second guess -10% if the default fails) | C37: =IFERROR(IRR(D24:AJ24),IFERROR(IRR(D24:AJ24,-0.1),"n/a")) -> 0.082939523

Sheet Checks
A1: Checks
A3: Model identities (must all be TRUE)
C4: Calculated
A5: Debt converged: calculated debt = pasted debt | B5: =ABS(C5-Inputs!C32)<0.000001 -> TRUE | C5: =Operations!C33 -> 369.5367
A6: Uses converged: calculated uses = pasted uses | B6: =ABS(C6-Inputs!C33)<0.000001 -> TRUE | C6: =Construction!C15 -> 415.44543
A7: Debt balance at COD = debt | B7: =ABS(Construction!C17-Inputs!C32)<0.000001 -> TRUE
A8: Principal over the tenor sums to the debt | B8: =ABS(Operations!C37-Inputs!C32)<0.000001 -> TRUE
A9: Balance is zero at maturity | B9: =ABS(Operations!C36)<0.000001 -> TRUE
A10: Sources = uses (debt + equity = total uses) | B10: =ABS(Construction!C17+Construction!C18-Construction!C15)<0.000001 -> TRUE
A11: Gearing within the cap | B11: =Inputs!C32<=Inputs!C20*Construction!C15+0.000001 -> TRUE
A12: Sponsor-case LLCR = sculpting DSCR in every tenor year | B12: =SUMPRODUCT(Operations!D6:AG6,ABS(Operations!D22:AG22-Operations!C34))<0.000000001 -> TRUE
A13: Frozen debt: debt service on Analysis = sizing schedule | B13: =SUMPRODUCT(ABS(Analysis!D12:AG12-Operations!D16:AG16))<0.000000001 -> TRUE
A14: Capex profile sums to 1 and is fully placed | B14: =AND(ABS(SUM(Inputs!C7:C9)-1)<0.000000001,ABS(SUM(Construction!C6:E6)-Inputs!C6)<0.000001) -> TRUE
A15: Layout limits: 1-3 construction years, tenor < operating years <= 30 | B15: =AND(Inputs!C5>=1,Inputs!C5<=3,Inputs!C18>=1,Inputs!C18<Inputs!C10,Inputs!C10<=30) -> TRUE
A17: Overall | B17: =IF(AND(B5:B15),"ALL CHECKS PASS","CHECK FAILED") -> ALL CHECKS PASS
A19: Information (not a pass/fail test): smallest principal payment is not negative | B19: =Operations!C38>=0 -> TRUE
A21: Cross-check against the Python model: shipped inputs, 'downside' stress active
A22: Reference values from project-finance-lab run --config examples/project_hypothetical.json. They are expected to differ once inputs change; excel/regression tests other inputs.
A24: Metric | B24: Python | C24: Workbook | D24: Match
A25: Debt | B25: 369.5367 | C25: =Operations!C33 -> 369.5367 | D25: =IF(ABS(C25-B25)<0.000001,"match","MISMATCH") -> match
A26: Total uses | B26: 415.44543 | C26: =Construction!C15 -> 415.44543 | D26: =IF(ABS(C26-B26)<0.000001,"match","MISMATCH") -> match
A27: Sculpting DSCR | B27: 1.35 | C27: =Operations!C34 -> 1.35 | D27: =IF(ABS(C27-B27)<0.000001,"match","MISMATCH") -> match
A28: Minimum DSCR, downside case | B28: 1.0953855 | C28: =Analysis!C28 -> 1.0953855 | D28: =IF(ABS(C28-B28)<0.000001,"match","MISMATCH") -> match
A29: LLCR at COD, downside case | B29: 1.1061578 | C29: =Analysis!C30 -> 1.1061578 | D29: =IF(ABS(C29-B29)<0.000001,"match","MISMATCH") -> match
A30: PLCR at COD, downside case | B30: 1.3349882 | C30: =Analysis!C32 -> 1.3349882 | D30: =IF(ABS(C30-B30)<0.000001,"match","MISMATCH") -> match
A31: Lock-up years, downside case | B31: 18 | C31: =Analysis!C33 -> 18 | D31: =IF(ABS(C31-B31)<0.000001,"match","MISMATCH") -> match
A32: Equity IRR, downside case | B32: 0.082939523 | C32: =Analysis!C37 -> 0.082939523 | D32: =IF(ABS(C32-B32)<0.000001,"match","MISMATCH") -> match
